pairsnp/__init__.py
pairsnp/pairsnp.py
pairsnp/tests/__init__.py
pairsnp/tests/test_alignments.py
pairsnp-0.0.7.dist-info/METADATA
pairsnp-0.0.7.dist-info/RECORD
pairsnp-0.0.7.dist-info/WHEEL
pairsnp-0.0.7.dist-info/entry_points.txt
pairsnp-0.0.7.dist-info/top_level.txt
