Metadata-Version: 2.1
Name: pairsnp
Version: 0.0.7
Summary: A simple package for calculating pairwise SNP distances
Home-page: https://github.com/gtonkinhill/pairsnp/
Author: Gerry Tonkin-Hill
Author-email: g.tonkinhill@gmail.com
License: UNKNOWN
Platform: UNKNOWN
Classifier: Programming Language :: Python :: 3.6
Classifier: License :: OSI Approved :: MIT License
Classifier: Operating System :: OS Independent
Requires-Dist: numpy
Requires-Dist: scipy
